p2pcam/__init__.py
p2pcam-0.0.3.dist-info/LICENSE
p2pcam-0.0.3.dist-info/METADATA
p2pcam-0.0.3.dist-info/WHEEL
p2pcam-0.0.3.dist-info/top_level.txt
p2pcam-0.0.3.dist-info/RECORD
