Metadata-Version: 2.1
Name: p2pcam
Version: 0.0.3
Summary: A package to talk to p2p cameras
Home-page: https://github.com/indykoning/PyPI_p2pcam
Author: IndyKoning
License: UNKNOWN
Platform: UNKNOWN
Classifier: Programming Language :: Python :: 3
Classifier: License :: OSI Approved :: MIT License
Classifier: Operating System :: OS Independent
